LICENSE
README.md
pyproject.toml
setup.py
contest_cli/__init__.py
contest_cli/__main__.py
contest_cli/cli.py
contest_cli/client.py
contest_cli/constants.py
contest_cli/display.py
contest_cli/utils.py
contest_cli.egg-info/PKG-INFO
contest_cli.egg-info/SOURCES.txt
contest_cli.egg-info/dependency_links.txt
contest_cli.egg-info/entry_points.txt
contest_cli.egg-info/requires.txt
contest_cli.egg-info/top_level.txt
tests/__init__.py
tests/test_client.py
tests/test_utils.py