Metadata-Version: 2.1
Name: contest-cli
Version: 0.0.2
Summary: Programming contest information for those who live in the terminal
Home-page: http://packages.python.org/contest-cli
Author: Liam Scalzulli
Author-email: liamscalzulli@gmail.com
License: BSD
Project-URL: Source Code, https://github.com/terror/contest-cli
Keywords: utility,programming,contests,cli
Platform: UNKNOWN
Classifier: Development Status :: 3 - Alpha
Classifier: Topic :: Utilities
Classifier: License :: OSI Approved :: MIT License
Requires-Python: >=3.7
